pgmig/__init__.py
pgmig/mypy.toml
pgmig/py.typed
pgmig-0.0.1.dist-info/LICENSE
pgmig-0.0.1.dist-info/METADATA
pgmig-0.0.1.dist-info/WHEEL
pgmig-0.0.1.dist-info/RECORD
